spssvalidate/__init__.py
spssvalidate/ai_model.py
spssvalidate/validator.py
tests/__init__.py
tests/test_validator.py
spssvalidate-0.1.2.dist-info/METADATA
spssvalidate-0.1.2.dist-info/WHEEL
spssvalidate-0.1.2.dist-info/top_level.txt
spssvalidate-0.1.2.dist-info/RECORD
