Metadata-Version: 2.2
Name: spssvalidate
Version: 0.1.2
Summary: A library to validate the authenticity and integrity of star maps.
Home-page: https://github.com/Sumedh1599export/spssvalidate
Author: Sumedh Patil
Author-email: admin@aipresso.uk
Dynamic: author
Dynamic: author-email
Dynamic: home-page
Dynamic: summary
